{
  "description": "Not COD related in any way. \r\n- From The Jefferson's",
  "title": "Nigga Please",
  "caption": [
    {
      "start": "0.78",
      "duration": "6.079",
      "text": "well it must be at least a hundred"
    },
    { "start": "3.54", "duration": "3.319", "text": "dollars 350." },
    {
      "start": "8.179",
      "duration": "8.281",
      "text": "350 dollars for a watch [\u00a0__\u00a0] please"
    },
    { "start": "13.14", "duration": "3.32", "text": "[Applause]" }
  ]
}
